{
  "CF98749325": {
    "contest_id": 1291,
    "language": "GNU C++14",
    "path": "codeforces\\1291\\A.cpp",
    "platform": "Codeforces",
    "problem_index": "A",
    "problem_name": "Even But Not Even",
    "problem_url": "https://codeforces.com/contest/1291/problem/A",
    "submission_id": "CF98749325",
    "submission_url": "https://codeforces.com/contest/1291/submission/98749325",
    "tags": [
      "greedy",
      "math",
      "strings",
      "*900"
    ],
    "timestamp": "Nov/17/2020 23:13"
  }
}